tree_sitter_dockerfile/__init__.py
tree_sitter_dockerfile/__init__.pyi
tree_sitter_dockerfile/_binding.abi3.so
tree_sitter_dockerfile/binding.c
tree_sitter_dockerfile/py.typed
tree_sitter_dockerfile/queries/highlights.scm
tree_sitter_dockerfile-0.2.0.dist-info/licenses/LICENSE
tree_sitter_dockerfile-0.2.0.dist-info/METADATA
tree_sitter_dockerfile-0.2.0.dist-info/WHEEL
tree_sitter_dockerfile-0.2.0.dist-info/top_level.txt
tree_sitter_dockerfile-0.2.0.dist-info/RECORD
