Metadata-Version: 2.4
Name: tree-sitter-dockerfile
Version: 0.2.0
Summary: Dockerfile grammar for tree-sitter
License: MIT
Project-URL: Homepage, https://github.com/camdencheek/tree-sitter-dockerfile
Keywords: incremental,parsing,tree-sitter,dockerfile
Classifier: Intended Audience :: Developers
Classifier: License :: OSI Approved :: MIT License
Classifier: Topic :: Software Development :: Compilers
Classifier: Topic :: Text Processing :: Linguistic
Classifier: Typing :: Typed
Requires-Python: >=3.8
License-File: LICENSE
Provides-Extra: core
Requires-Dist: tree-sitter~=0.21; extra == "core"
Dynamic: license-file
